{
    "SkeletonBatches": [],
    "HierarchyTrees": [],
    "Name": "SceneRoot",
    "RootComponent": {
        "polymorphic_id": 1073741824,
        "ptr_wrapper": {
            "valid": 1,
            "data": {
                "Name": "SceneRoot's root",
                "ComponentTransform": {
                    "Position": {
                        "x": 0.0,
                        "y": 0.0,
                        "z": 0.0
                    },
                    "Rotation": {
                        "x": 0.0,
                        "y": 0.0,
                        "z": 0.0,
                        "w": 1.0
                    },
                    "Scale": {
                        "x": 1.0,
                        "y": 1.0,
                        "z": 1.0
                    }
                },
                "CollisionObj": {
                    "ptr_wrapper": {
                        "valid": 0
                    }
                },
                "Children": [
                    {
                        "polymorphic_id": 2147483649,
                        "polymorphic_name": "GEE::LightProbeComponent",
                        "ptr_wrapper": {
                            "valid": 1,
                            "data": {
                                "Shape": 0,
                                "OptionalFilepath": "C:\\Users\\48511\\source\\repos\\swetroniusz\\game-engine-engine\\Projects\\Extended Essay\\white.hdr",
                                "ProbeIntensity": 1.0,
                                "Component": {
                                    "Name": "A LightProbeComponent",
                                    "ComponentTransform": {
                                        "Position": {
                                            "x": 0.0,
                                            "y": 0.0,
                                            "z": 0.0
                                        },
                                        "Rotation": {
                                            "x": 0.0,
                                            "y": 0.0,
                                            "z": 0.0,
                                            "w": 1.0
                                        },
                                        "Scale": {
                                            "x": 1.0,
                                            "y": 1.0,
                                            "z": 1.0
                                        }
                                    },
                                    "CollisionObj": {
                                        "ptr_wrapper": {
                                            "valid": 0
                                        }
                                    },
                                    "Children": []
                                }
                            }
                        }
                    }
                ]
            }
        }
    },
    "Children": [
        {
            "polymorphic_id": 1073741824,
            "ptr_wrapper": {
                "valid": 1,
                "data": {
                    "Name": "A Camera",
                    "RootComponent": {
                        "polymorphic_id": 1073741824,
                        "ptr_wrapper": {
                            "valid": 1,
                            "data": {
                                "Name": "A Camera's root",
                                "ComponentTransform": {
                                    "Position": {
                                        "x": 0.0,
                                        "y": 0.0,
                                        "z": 0.0
                                    },
                                    "Rotation": {
                                        "x": 0.0,
                                        "y": 0.0,
                                        "z": 0.0,
                                        "w": 1.0
                                    },
                                    "Scale": {
                                        "x": 1.0,
                                        "y": 1.0,
                                        "z": 1.0
                                    }
                                },
                                "CollisionObj": {
                                    "ptr_wrapper": {
                                        "valid": 0
                                    }
                                },
                                "Children": [
                                    {
                                        "polymorphic_id": 2147483650,
                                        "polymorphic_name": "GEE::CameraComponent",
                                        "ptr_wrapper": {
                                            "valid": 1,
                                            "data": {
                                                "Projection": {
                                                    "row0": {
                                                        "x": 1.0,
                                                        "y": 0.0,
                                                        "z": 0.0,
                                                        "w": 0.0
                                                    },
                                                    "row1": {
                                                        "x": 0.0,
                                                        "y": 1.0,
                                                        "z": 0.0,
                                                        "w": 0.0
                                                    },
                                                    "row2": {
                                                        "x": 0.0,
                                                        "y": 0.0,
                                                        "z": -1.0002000331878663,
                                                        "w": -1.0
                                                    },
                                                    "row3": {
                                                        "x": 0.0,
                                                        "y": 0.0,
                                                        "z": -0.020002000033855439,
                                                        "w": 0.0
                                                    }
                                                },
                                                "Active": true,
                                                "Component": {
                                                    "Name": "A CameraComponent",
                                                    "ComponentTransform": {
                                                        "Position": {
                                                            "x": 0.0,
                                                            "y": 0.0,
                                                            "z": 0.0
                                                        },
                                                        "Rotation": {
                                                            "x": 0.0,
                                                            "y": 0.0,
                                                            "z": 0.0,
                                                            "w": 1.0
                                                        },
                                                        "Scale": {
                                                            "x": 1.0,
                                                            "y": 1.0,
                                                            "z": 1.0
                                                        }
                                                    },
                                                    "CollisionObj": {
                                                        "ptr_wrapper": {
                                                            "valid": 0
                                                        }
                                                    },
                                                    "Children": []
                                                }
                                            }
                                        }
                                    }
                                ]
                            }
                        }
                    },
                    "Children": [
                        {
                            "polymorphic_id": 2147483651,
                            "polymorphic_name": "GEE::FreeRoamingController",
                            "ptr_wrapper": {
                                "valid": 1,
                                "data": {
                                    "PossessedActorName": "A Camera",
                                    "bHideCursor": true,
                                    "bLockMouseAtCenter": true,
                                    "Actor": {
                                        "Name": "A FreeRoamingController",
                                        "RootComponent": {
                                            "polymorphic_id": 1073741824,
                                            "ptr_wrapper": {
                                                "valid": 1,
                                                "data": {
                                                    "Name": "A FreeRoamingController's root",
                                                    "ComponentTransform": {
                                                        "Position": {
                                                            "x": 0.0,
                                                            "y": 0.0,
                                                            "z": 0.0
                                                        },
                                                        "Rotation": {
                                                            "x": 0.0,
                                                            "y": 0.0,
                                                            "z": 0.0,
                                                            "w": 1.0
                                                        },
                                                        "Scale": {
                                                            "x": 1.0,
                                                            "y": 1.0,
                                                            "z": 1.0
                                                        }
                                                    },
                                                    "CollisionObj": {
                                                        "ptr_wrapper": {
                                                            "valid": 0
                                                        }
                                                    },
                                                    "Children": []
                                                }
                                            }
                                        },
                                        "Children": []
                                    }
                                }
                            }
                        }
                    ]
                }
            }
        },
        {
            "polymorphic_id": 1073741824,
            "ptr_wrapper": {
                "valid": 1,
                "data": {
                    "Name": "Default sphere",
                    "RootComponent": {
                        "polymorphic_id": 1073741824,
                        "ptr_wrapper": {
                            "valid": 1,
                            "data": {
                                "Name": "Default sphere's root",
                                "ComponentTransform": {
                                    "Position": {
                                        "x": 0.0,
                                        "y": 0.0,
                                        "z": -3.0
                                    },
                                    "Rotation": {
                                        "x": 0.0,
                                        "y": 0.0,
                                        "z": 0.0,
                                        "w": 1.0
                                    },
                                    "Scale": {
                                        "x": 1.0,
                                        "y": 1.0,
                                        "z": 1.0
                                    }
                                },
                                "CollisionObj": {
                                    "ptr_wrapper": {
                                        "valid": 0
                                    }
                                },
                                "Children": [
                                    {
                                        "polymorphic_id": 2147483652,
                                        "polymorphic_name": "GEE::ModelComponent",
                                        "ptr_wrapper": {
                                            "valid": 1,
                                            "data": {
                                                "RenderAsBillboard": false,
                                                "MeshInstances": [
                                                    {
                                                        "ptr_wrapper": {
                                                            "valid": 1,
                                                            "data": {
                                                                "MeshTreePath": "ENG_SPHERE",
                                                                "MeshNodeName": "Sphere",
                                                                "MeshSpecificName": "Sphere",
                                                                "MaterialInst": {
                                                                    "ptr_wrapper": {
                                                                        "id": 0
                                                                    }
                                                                }
                                                            }
                                                        }
                                                    }
                                                ],
                                                "SkelInfoBatchID": -1,
                                                "SkelInfoID": -1,
                                                "RenderableComponent": {
                                                    "Hide": false,
                                                    "CastsShadow": true,
                                                    "Component": {
                                                        "Name": "A ModelComponent",
                                                        "ComponentTransform": {
                                                            "Position": {
                                                                "x": 0.0,
                                                                "y": 0.0,
                                                                "z": 0.0
                                                            },
                                                            "Rotation": {
                                                                "x": 0.0,
                                                                "y": 0.0,
                                                                "z": 0.0,
                                                                "w": 1.0
                                                            },
                                                            "Scale": {
                                                                "x": 1.0,
                                                                "y": 1.0,
                                                                "z": 1.0
                                                            }
                                                        },
                                                        "CollisionObj": {
                                                            "ptr_wrapper": {
                                                                "valid": 0
                                                            }
                                                        },
                                                        "Children": []
                                                    }
                                                }
                                            }
                                        }
                                    },
                                    {
                                        "polymorphic_id": 2147483653,
                                        "polymorphic_name": "GEE::LightComponent",
                                        "ptr_wrapper": {
                                            "valid": 1,
                                            "data": {
                                                "Lighttype": 1,
                                                "Ambient": {
                                                    "x": 0.0,
                                                    "y": 0.0,
                                                    "z": 0.0
                                                },
                                                "Diffuse": {
                                                    "x": 1.0,
                                                    "y": 1.0,
                                                    "z": 1.0
                                                },
                                                "Specular": {
                                                    "x": 0.5,
                                                    "y": 0.5,
                                                    "z": 0.5
                                                },
                                                "Attenuation": 1.0,
                                                "CutOff": 1.0,
                                                "OuterCutOff": 1.0,
                                                "Far": 7.085196018218994,
                                                "ShadowBias": 0.0010000000474974514,
                                                "bShadowMapCullFronts": true,
                                                "Component": {
                                                    "Name": "A LightComponent",
                                                    "ComponentTransform": {
                                                        "Position": {
                                                            "x": 0.0,
                                                            "y": 0.0,
                                                            "z": 2.0
                                                        },
                                                        "Rotation": {
                                                            "x": 0.0,
                                                            "y": 0.0,
                                                            "z": 0.0,
                                                            "w": 1.0
                                                        },
                                                        "Scale": {
                                                            "x": 7.085196018218994,
                                                            "y": 7.085196018218994,
                                                            "z": 7.085196018218994
                                                        }
                                                    },
                                                    "CollisionObj": {
                                                        "ptr_wrapper": {
                                                            "valid": 0
                                                        }
                                                    },
                                                    "Children": []
                                                }
                                            }
                                        }
                                    }
                                ]
                            }
                        }
                    },
                    "Children": []
                }
            }
        },
        {
            "polymorphic_id": 1073741824,
            "ptr_wrapper": {
                "valid": 1,
                "data": {
                    "Name": "An Actor",
                    "RootComponent": {
                        "polymorphic_id": 1073741824,
                        "ptr_wrapper": {
                            "valid": 1,
                            "data": {
                                "Name": "An Actor's root",
                                "ComponentTransform": {
                                    "Position": {
                                        "x": 0.0,
                                        "y": -0.8500000238418579,
                                        "z": -1.5
                                    },
                                    "Rotation": {
                                        "x": 0.017452405765652658,
                                        "y": 0.0,
                                        "z": 0.0,
                                        "w": 0.9998477101325989
                                    },
                                    "Scale": {
                                        "x": 1.0,
                                        "y": 1.0,
                                        "z": 1.0
                                    }
                                },
                                "CollisionObj": {
                                    "ptr_wrapper": {
                                        "valid": 0
                                    }
                                },
                                "Children": [
                                    {
                                        "polymorphic_id": 1073741824,
                                        "ptr_wrapper": {
                                            "valid": 1,
                                            "data": {
                                                "Name": "C:\\Users\\48511\\Desktop\\Maths IA\\mathsbook.glb",
                                                "ComponentTransform": {
                                                    "Position": {
                                                        "x": 0.0,
                                                        "y": 0.0,
                                                        "z": 0.0
                                                    },
                                                    "Rotation": {
                                                        "x": 0.0,
                                                        "y": 0.0,
                                                        "z": 0.0,
                                                        "w": 1.0
                                                    },
                                                    "Scale": {
                                                        "x": 1.0,
                                                        "y": 1.0,
                                                        "z": 1.0
                                                    }
                                                },
                                                "CollisionObj": {
                                                    "ptr_wrapper": {
                                                        "valid": 0
                                                    }
                                                },
                                                "Children": [
                                                    {
                                                        "polymorphic_id": 4,
                                                        "ptr_wrapper": {
                                                            "valid": 1,
                                                            "data": {
                                                                "RenderAsBillboard": false,
                                                                "MeshInstances": [
                                                                    {
                                                                        "ptr_wrapper": {
                                                                            "valid": 1,
                                                                            "data": {
                                                                                "MeshTreePath": "C:\\Users\\48511\\Desktop\\Maths IA\\mathsbook.glb",
                                                                                "MeshNodeName": "Cube",
                                                                                "MeshSpecificName": "Cube.001",
                                                                                "MaterialInst": {
                                                                                    "ptr_wrapper": {
                                                                                        "id": 0
                                                                                    }
                                                                                }
                                                                            }
                                                                        }
                                                                    }
                                                                ],
                                                                "SkelInfoBatchID": -1,
                                                                "SkelInfoID": -1,
                                                                "RenderableComponent": {
                                                                    "Hide": false,
                                                                    "CastsShadow": true,
                                                                    "Component": {
                                                                        "Name": "C:\\Users\\48511\\Desktop\\Maths IA\\mathsbook.glbRootMeshes",
                                                                        "ComponentTransform": {
                                                                            "Position": {
                                                                                "x": 0.0,
                                                                                "y": 0.0,
                                                                                "z": 0.0
                                                                            },
                                                                            "Rotation": {
                                                                                "x": -0.7071067690849304,
                                                                                "y": -0.0,
                                                                                "z": 0.0,
                                                                                "w": 0.7071067690849304
                                                                            },
                                                                            "Scale": {
                                                                                "x": 1.0,
                                                                                "y": 1.0,
                                                                                "z": 1.0
                                                                            }
                                                                        },
                                                                        "CollisionObj": {
                                                                            "ptr_wrapper": {
                                                                                "valid": 0
                                                                            }
                                                                        },
                                                                        "Children": []
                                                                    }
                                                                }
                                                            }
                                                        }
                                                    }
                                                ]
                                            }
                                        }
                                    }
                                ]
                            }
                        }
                    },
                    "Children": []
                }
            }
        }
    ],
    "bWindowFullscreen": false,
    "WindowTitle": "game-engine-engine",
    "Video": {
        "AmbientOcclusionSamples": 64,
        "bVSync": false,
        "bBloom": true,
        "AAType": 1,
        "AALevel": 4,
        "MonitorGamma": 2.200000047683716,
        "POMLevel": 1,
        "ShadowLevel": 1,
        "TMType": 1,
        "Max2DShadows": 16,
        "Max3DShadows": 16
    },
    "bDebugRenderComponents": true
}